odoo/addons/fs_attachment/README.rst
odoo/addons/fs_attachment/__init__.py
odoo/addons/fs_attachment/__manifest__.py
odoo/addons/fs_attachment/fs_stream.py
odoo/addons/fs_attachment/hooks.py
odoo/addons/fs_attachment/i18n/de.po
odoo/addons/fs_attachment/i18n/es.po
odoo/addons/fs_attachment/i18n/fr.po
odoo/addons/fs_attachment/i18n/fs_attachment.pot
odoo/addons/fs_attachment/i18n/it.po
odoo/addons/fs_attachment/i18n/zh_CN.po
odoo/addons/fs_attachment/models/__init__.py
odoo/addons/fs_attachment/models/fs_file_gc.py
odoo/addons/fs_attachment/models/fs_storage.py
odoo/addons/fs_attachment/models/ir_attachment.py
odoo/addons/fs_attachment/models/ir_binary.py
odoo/addons/fs_attachment/models/strtobool.py
odoo/addons/fs_attachment/readme/CONTRIBUTORS.md
odoo/addons/fs_attachment/readme/DESCRIPTION.md
odoo/addons/fs_attachment/readme/HISTORY.md
odoo/addons/fs_attachment/readme/USAGE.md
odoo/addons/fs_attachment/readme/newsfragments/.gitignore
odoo/addons/fs_attachment/security/fs_file_gc.xml
odoo/addons/fs_attachment/static/description/icon.png
odoo/addons/fs_attachment/static/description/index.html
odoo/addons/fs_attachment/tests/__init__.py
odoo/addons/fs_attachment/tests/common.py
odoo/addons/fs_attachment/tests/test_fs_attachment.py
odoo/addons/fs_attachment/tests/test_fs_attachment_file_like_adapter.py
odoo/addons/fs_attachment/tests/test_fs_attachment_internal_url.py
odoo/addons/fs_attachment/tests/test_fs_storage.py
odoo/addons/fs_attachment/tests/test_stream.py
odoo/addons/fs_attachment/views/fs_storage.xml
odoo_addon_fs_attachment-18.0.2.2.0.3.dist-info/METADATA
odoo_addon_fs_attachment-18.0.2.2.0.3.dist-info/WHEEL
odoo_addon_fs_attachment-18.0.2.2.0.3.dist-info/top_level.txt
odoo_addon_fs_attachment-18.0.2.2.0.3.dist-info/RECORD
