Metadata-Version: 2.1
Name: odoo-addon-fs_attachment
Version: 18.0.2.2.0.3
Requires-Python: >=3.10
Requires-Dist: fsspec>=2025.3.0
Requires-Dist: odoo-addon-fs_storage==18.0.*
Requires-Dist: odoo==18.0.*
Requires-Dist: python_slugify
Summary: Store attachments on external object store
Home-page: https://github.com/OCA/storage
License: AGPL-3
Author: Camptocamp, ACSONE SA/NV, Odoo Community Association (OCA)
Author-email: support@odoo-community.org
Classifier: Programming Language :: Python
Classifier: Framework :: Odoo
Classifier: Framework :: Odoo :: 18.0
Classifier: License :: OSI Approved :: GNU Affero General Public License v3
Classifier: Development Status :: 4 - Beta
